konoha/__init__.py
konoha/py.typed
konoha/sentence_tokenizer.py
konoha/word_tokenizer.py
konoha/api/__init__.py
konoha/api/server.py
konoha/api/v1/__init__.py
konoha/api/v1/batch_tokenization.py
konoha/api/v1/tokenization.py
konoha/data/__init__.py
konoha/data/resource.py
konoha/data/token.py
konoha/word_tokenizers/__init__.py
konoha/word_tokenizers/character_tokenizer.py
konoha/word_tokenizers/janome_tokenizer.py
konoha/word_tokenizers/konoha_api_tokenizer.py
konoha/word_tokenizers/kytea_tokenizer.py
konoha/word_tokenizers/mecab_tokenizer.py
konoha/word_tokenizers/nagisa_tokenizer.py
konoha/word_tokenizers/sentencepiece_tokenizer.py
konoha/word_tokenizers/sudachi_tokenizer.py
konoha/word_tokenizers/tokenizer.py
konoha/word_tokenizers/whitespace_tokenizer.py
konoha-5.6.0.dist-info/METADATA
konoha-5.6.0.dist-info/WHEEL
konoha-5.6.0.dist-info/licenses/LICENSE
konoha-5.6.0.dist-info/RECORD
