Metadata-Version: 2.4
Name: konoha
Version: 5.6.0
Summary: Add your description here
Author-email: himkt <himkt@klis.tsukuba.ac.jp>
License-Expression: MIT
License-File: LICENSE
Requires-Python: >=3.9
Requires-Dist: requests<3.0.0
Provides-Extra: all
Requires-Dist: boto3~=1.34.0; extra == 'all'
Requires-Dist: fastapi<1.0.0; extra == 'all'
Requires-Dist: janome~=0.5.0; extra == 'all'
Requires-Dist: kytea~=0.1.0; extra == 'all'
Requires-Dist: nagisa~=0.2.10; extra == 'all'
Requires-Dist: natto-py~=1.0.0; extra == 'all'
Requires-Dist: sentencepiece~=0.1.85; extra == 'all'
Requires-Dist: sudachidict-core==20230927; extra == 'all'
Requires-Dist: uvicorn<0.26.0; extra == 'all'
Provides-Extra: janome
Requires-Dist: janome~=0.5.0; extra == 'janome'
Provides-Extra: kytea
Requires-Dist: kytea~=0.1.0; extra == 'kytea'
Provides-Extra: mecab
Requires-Dist: natto-py~=1.0.0; extra == 'mecab'
Provides-Extra: nagisa
Requires-Dist: nagisa~=0.2.10; extra == 'nagisa'
Provides-Extra: remote
Requires-Dist: boto3~=1.34.0; extra == 'remote'
Provides-Extra: sentencepiece
Requires-Dist: sentencepiece~=0.1.85; extra == 'sentencepiece'
Provides-Extra: server
Requires-Dist: fastapi<1.0.0; extra == 'server'
Requires-Dist: uvicorn<0.26.0; extra == 'server'
Provides-Extra: sudachi
Requires-Dist: sudachidict-core==20230927; extra == 'sudachi'
Requires-Dist: sudachipy~=0.6.8; extra == 'sudachi'
